dsflow/__init__.py
dsflow/dataset.py
dsflow-0.0.1.dist-info/METADATA
dsflow-0.0.1.dist-info/WHEEL
dsflow-0.0.1.dist-info/top_level.txt
dsflow-0.0.1.dist-info/RECORD
